[
  { "id": 21351, "name": "Ненецкий АО" },
  { "id": 20936, "name": "Ханты-Мансийский АО" },
  { "id": 20924, "name": "Чукотский АО" },
  { "id": 20984, "name": "Ямало-Ненецкий АО" },
  { "id": 1011969, "name": "Москва" },
  { "id": 1012040, "name": "Санкт-Петербург" },
  { "id": 1011984, "name": "Новосибирск" },
  { "id": 1012052, "name": "Екатеринбург" },
  { "id": 1011981, "name": "Нижний Новгород" },
  { "id": 1012054, "name": "Казань" },
  { "id": 1011874, "name": "Челябинск" },
  { "id": 1011985, "name": "Омск" },
  { "id": 1012029, "name": "Самара" },
  { "id": 1012013, "name": "Ростов-на-Дону" },
  { "id": 1011867, "name": "Уфа" },
  { "id": 1011941, "name": "Красноярск" },
  { "id": 1011993, "name": "Пермь" },
  { "id": 1012077, "name": "Воронеж" },
  { "id": 1012068, "name": "Волгоград" },
  { "id": 1011905, "name": "Краснодар" },
  { "id": 1012036, "name": "Саратов" },
  { "id": 1012062, "name": "Тюмень" },
  { "id": 1012032, "name": "Тольятти" },
  { "id": 1012064, "name": "Ижевск" },
  { "id": 1011853, "name": "Барнаул" },
  { "id": 1011896, "name": "Иркутск" },
  { "id": 1012067, "name": "Ульяновск" },
  { "id": 1011918, "name": "Хабаровск" },
  { "id": 1012084, "name": "Ярославль" },
  { "id": 1012008, "name": "Владивосток" },
  { "id": 1011892, "name": "Махачкала" },
  { "id": 1012059, "name": "Томск" },
  { "id": 1011987, "name": "Оренбург" },
  { "id": 1011909, "name": "Кемерово" },
  { "id": 1011912, "name": "Новокузнецк" },
  { "id": 1012017, "name": "Рязань" },
  { "id": 1011862, "name": "Астрахань" },
  { "id": 1012055, "name": "Набережные Челны" },
  { "id": 1011996, "name": "Пенза" },
  { "id": 1011947, "name": "Липецк" },
  { "id": 1011925, "name": "Киров" },
  { "id": 1012060, "name": "Тула" },
  { "id": 9040951, "name": "Чебоксары" },
  { "id": 1011914, "name": "Калининград" },
  { "id": 1011937, "name": "Курск" },
  { "id": 1011870, "name": "Улан - Удэ" },
  { "id": 1012043, "name": "Ставрополь" },
  { "id": 1011951, "name": "Балашиха" },
  { "id": 1011881, "name": "Магнитогорск" },
  { "id": 1012061, "name": "Тверь" },
  { "id": 1011898, "name": "Иваново" },
  { "id": 1011869, "name": "Брянск" },
  { "id": 1011907, "name": "Сочи" },
  { "id": 1011868, "name": "Белгород" },
  { "id": 1012048, "name": "Нижний Тагил" },
  { "id": 1012073, "name": "Владимир" },
  { "id": 1011859, "name": "Архангельск" },
  { "id": 1011924, "name": "Сургут" },
  { "id": 9040996, "name": "Чита" },
  { "id": 1011928, "name": "Калуга" },
  { "id": 1012038, "name": "Смоленск" },
  { "id": 1012069, "name": "Волжский" },
  { "id": 1011916, "name": "Курган" },
  { "id": 1011990, "name": "Орёл" },
  { "id": 1012074, "name": "Череповец" },
  { "id": 1012075, "name": "Вологда" },
  { "id": 1011950, "name": "Саранск" },
  { "id": 1012037, "name": "Владикавказ" },
  { "id": 1012018, "name": "Якутск" },
  { "id": 1011976, "name": "Мурманск" },
  { "id": 1011963, "name": "Подольск" },
  { "id": 1012057, "name": "Тамбов" },
  { "id": 9040919, "name": "Грозный" },
  { "id": 1011866, "name": "Стерлитамак" },
  { "id": 1011935, "name": "Петрозаводск" },
  { "id": 1011934, "name": "Кострома" },
  { "id": 1011923, "name": "Нижневартовск" },
  { "id": 1011906, "name": "Новороссийск" },
  { "id": 1011949, "name": "Йошкар-Ола" },
  { "id": 9040997, "name": "Комсомольск-на-Амуре" },
  { "id": 1012015, "name": "Таганрог" },
  { "id": 1011931, "name": "Сыктывкар" },
  { "id": 1011956, "name": "Химки" },
  { "id": 1011901, "name": "Нальчик" },
  { "id": 1012014, "name": "Шахты" },
  { "id": 9040952, "name": "Нижнекамск" },
  { "id": 1011895, "name": "Братск" },
  { "id": 1011980, "name": "Дзержинск" },
  { "id": 1011988, "name": "Орск" },
  { "id": 1011894, "name": "Ангарск" },
  { "id": 1011858, "name": "Благовещенск" },
  { "id": 1012034, "name": "Энгельс" },
  { "id": 9040930, "name": "Старый Оскол" },
  { "id": 1011977, "name": "Великий Новгород" },
  { "id": 1011958, "name": "Королёв" },
  { "id": 1012010, "name": "Псков" },
  { "id": 1011854, "name": "Бийск" },
  { "id": 9040982, "name": "Мытищи" },
  { "id": 1011913, "name": "Прокопьевск" },
  { "id": 1012027, "name": "Южно-Сахалинск" },
  { "id": 1012033, "name": "Балаково" },
  { "id": 9040973, "name": "Рыбинск" },
  { "id": 9040927, "name": "Армавир" },
  { "id": 9040939, "name": "Люберцы" },
  { "id": 1011861, "name": "Северодвинск" },
  { "id": 1011899, "name": "Петропавловск-Камчатский" },
  { "id": 1011926, "name": "Абакан" },
  { "id": 1012058, "name": "Норильск" },
  { "id": 1012031, "name": "Сызрань" },
  { "id": 1012016, "name": "Волгодонск" },
  { "id": 1012012, "name": "Новочеркасск" },
  { "id": 1012045, "name": "Каменск - Уральский" },
  { "id": 1011889, "name": "Златоуст" },
  { "id": 1012007, "name": "Уссурийск" },
  { "id": 1011955, "name": "Электросталь" },
  { "id": 1011865, "name": "Салават" },
  { "id": 1012003, "name": "Находка" },
  { "id": 1012053, "name": "Альметьевск" },
  { "id": 1011882, "name": "Миасс" },
  { "id": 1011991, "name": "Березники" },
  { "id": 1011855, "name": "Рубцовск" },
  { "id": 1011878, "name": "Копейск" },
  { "id": 1012042, "name": "Пятигорск" },
  { "id": 9040985, "name": "Красногорск" },
  { "id": 1011852, "name": "Майкоп" },
  { "id": 1011957, "name": "Коломна" },
  { "id": 1011962, "name": "Одинцово" },
  { "id": 1012071, "name": "Ковров" },
  { "id": 9051389, "name": "Хасавюрт" },
  { "id": 9040921, "name": "Кисловодск" },
  { "id": 1011965, "name": "Серпухов" },
  { "id": 9040934, "name": "Новомосковск" },
  { "id": 1011863, "name": "Нефтекамск" },
  { "id": 9051426, "name": "Новочебоксарск" },
  { "id": 1011922, "name": "Нефтеюганск" },
  { "id": 1012049, "name": "Первоуральск" },
  { "id": 9040945, "name": "Щёлково" },
  { "id": 1011902, "name": "Черкесск" },
  { "id": 9040918, "name": "Дербент" },
  { "id": 9051375, "name": "Батайск" },
  { "id": 9040946, "name": "Орехово-Зуево" },
  { "id": 9040926, "name": "Невинномысск" },
  { "id": 9051382, "name": "Домодедово" },
  { "id": 1012066, "name": "Димитровград" },
  { "id": 9051404, "name": "Кызыл" },
  { "id": 9051420, "name": "Назрань" },
  { "id": 9040929, "name": "Камышин" },
  { "id": 1011929, "name": "Обнинск" },
  { "id": 9040958, "name": "Новый Уренгой" },
  { "id": 9051388, "name": "Каспийск" },
  { "id": 1012072, "name": "Муром" },
  { "id": 9040941, "name": "Раменское" },
  { "id": 1011968, "name": "Жуковский" },
  { "id": 1011964, "name": "Пушкино" },
  { "id": 9051428, "name": "Ноябрьск" },
  { "id": 1012041, "name": "Ессентуки" },
  { "id": 9040931, "name": "Елец" },
  { "id": 1011939, "name": "Ачинск" },
  { "id": 9051373, "name": "Артем" },
  { "id": 1011970, "name": "Сергиев Посад" },
  { "id": 1011978, "name": "Арзамас" },
  { "id": 1011927, "name": "Элиста" },
  { "id": 1012028, "name": "Новокуйбышевск" },
  { "id": 1011982, "name": "Бердск" },
  { "id": 1011961, "name": "Ногинск" },
  { "id": 9040983, "name": "Долгопрудный" },
  { "id": 9040956, "name": "Горно-Алтайск" },
  { "id": 1011870, "name": "Улан-Удэ" },
  { "id": 1011948, "name": "Магадан" },
  { "id": 1012085, "name": "Биробиджан" },
  { "id": 9051419, "name": "Нарьян-Мар" },
  { "id": 1011921, "name": "Ханты-Мансийск" },
  { "id": 9067760, "name": "Анадырь" },
  { "id": 1012079, "name": "Салехард" },
  { "id": 21250, "name": "Адыгея" },
  { "id": 20914, "name": "Алтай" },
  { "id": 20918, "name": "Башкортостан" },
  { "id": 20921, "name": "Бурятия" },
  { "id": 20925, "name": "Дагестан" },
  { "id": 21251, "name": "Ингушетия" },
  { "id": 20929, "name": "Кабардино-Балкария" },
  { "id": 21243, "name": "Калмыкия" },
  { "id": 20930, "name": "Карачаево-Черкесия" },
  { "id": 20942, "name": "Карелия" },
  { "id": 20940, "name": "Коми" },
  { "id": 21234, "name": "Марий Эл" },
  { "id": 20948, "name": "Мордовия" },
  { "id": 20963, "name": "Саха (Якутия)" },
  { "id": 21252, "name": "Северная Осетия-Алания" },
  { "id": 20971, "name": "Татарстан" },
  { "id": 21346, "name": "Тыва (Тува)" },
  { "id": 20978, "name": "Удмуртия" },
  { "id": 20938, "name": "Хакасия" },
  { "id": 21347, "name": "Чечня" },
  { "id": 21348, "name": "Чувашия" },
  { "id": 21385, "name": "Алтайский край" },
  { "id": 9047109, "name": "Забайкальский край" },
  { "id": 20928, "name": "Камчатский край" },
  { "id": 20931, "name": "Краснодарский край" },
  { "id": 20944, "name": "Красноярский край" },
  { "id": 20957, "name": "Пермский край" },
  { "id": 20959, "name": "Приморский край" },
  { "id": 20969, "name": "Ставропольский край" },
  { "id": 20935, "name": "Хабаровский край" },
  { "id": 20915, "name": "Амурская область" },
  { "id": 20916, "name": "Архангельская область" },
  { "id": 20917, "name": "Астраханская область" },
  { "id": 20919, "name": "Белгородская область" },
  { "id": 20920, "name": "Брянская область" },
  { "id": 20981, "name": "Владимирская область" },
  { "id": 20980, "name": "Волгоградская область" },
  { "id": 20982, "name": "Вологодская область" },
  { "id": 20983, "name": "Воронежская область" },
  { "id": 20927, "name": "Ивановская область" },
  { "id": 20926, "name": "Иркутская область" },
  { "id": 20933, "name": "Калининградская область" },
  { "id": 20939, "name": "Калужская область" },
  { "id": 20932, "name": "Кемеровская область" },
  { "id": 20937, "name": "Кировская область" },
  { "id": 20941, "name": "Костромская область" },
  { "id": 20934, "name": "Курганская область" },
  { "id": 20943, "name": "Курская область" },
  { "id": 20945, "name": "Ленинградская область" },
  { "id": 20946, "name": "Липецкая область" },
  { "id": 20947, "name": "Магаданская область" },
  { "id": 20949, "name": "Московская область" },
  { "id": 20951, "name": "Мурманская область" },
  { "id": 20953, "name": "Нижегородская область" },
  { "id": 20952, "name": "Новгородская область" },
  { "id": 20954, "name": "Новосибирская область" },
  { "id": 20955, "name": "Омская область" },
  { "id": 20956, "name": "Оренбургская область" },
  { "id": 21256, "name": "Орловская область" },
  { "id": 20958, "name": "Пензенская область" },
  { "id": 20960, "name": "Псковская область" },
  { "id": 20961, "name": "Ростовская область" },
  { "id": 20962, "name": "Рязанская область" },
  { "id": 20965, "name": "Самарская область" },
  { "id": 20966, "name": "Саратовская область" },
  { "id": 20964, "name": "Сахалинская область" },
  { "id": 20970, "name": "Свердловская область" },
  { "id": 20967, "name": "Смоленская область" },
  { "id": 20972, "name": "Тамбовская область" },
  { "id": 20976, "name": "Тверская область" },
  { "id": 20974, "name": "Томская область" },
  { "id": 20975, "name": "Тульская область" },
  { "id": 20977, "name": "Тюменская область" },
  { "id": 20979, "name": "Ульяновская область" },
  { "id": 20922, "name": "Челябинская область" },
  { "id": 20985, "name": "Ярославская область" },
  { "id": 21277, "name": "Еврейская АО" },{ "id": 21351, "name": "Ненецкий АО" },
  { "id": 20936, "name": "Ханты-Мансийский АО" },
  { "id": 20924, "name": "Чукотский АО" },
  { "id": 20984, "name": "Ямало-Ненецкий АО" },
  { "id": 1012040, "name": "Санкт-Петербург" },
  { "id": 1011984, "name": "Новосибирск" },
  { "id": 1012052, "name": "Екатеринбург" },
  { "id": 1011981, "name": "Нижний Новгород" },
  { "id": 1012054, "name": "Казань" },
  { "id": 1011874, "name": "Челябинск" },
  { "id": 1011985, "name": "Омск" },
  { "id": 1012029, "name": "Самара" },
  { "id": 1012013, "name": "Ростов-на-Дону" },
  { "id": 1011867, "name": "Уфа" },
  { "id": 1011941, "name": "Красноярск" },
  { "id": 1011993, "name": "Пермь" },
  { "id": 1012077, "name": "Воронеж" },
  { "id": 1012068, "name": "Волгоград" },
  { "id": 1011905, "name": "Краснодар" },
  { "id": 1012036, "name": "Саратов" },
  { "id": 1012062, "name": "Тюмень" },
  { "id": 1012032, "name": "Тольятти" },
  { "id": 1012064, "name": "Ижевск" },
  { "id": 1011853, "name": "Барнаул" },
  { "id": 1011896, "name": "Иркутск" },
  { "id": 1012067, "name": "Ульяновск" },
  { "id": 1011918, "name": "Хабаровск" },
  { "id": 1012084, "name": "Ярославль" },
  { "id": 1012008, "name": "Владивосток" },
  { "id": 1011892, "name": "Махачкала" },
  { "id": 1012059, "name": "Томск" },
  { "id": 1011987, "name": "Оренбург" },
  { "id": 1011909, "name": "Кемерово" },
  { "id": 1011912, "name": "Новокузнецк" },
  { "id": 1012017, "name": "Рязань" },
  { "id": 1011862, "name": "Астрахань" },
  { "id": 1012055, "name": "Набережные Челны" },
  { "id": 1011996, "name": "Пенза" },
  { "id": 1011947, "name": "Липецк" },
  { "id": 1011925, "name": "Киров" },
  { "id": 1012060, "name": "Тула" },
  { "id": 9040951, "name": "Чебоксары" },
  { "id": 1011914, "name": "Калининград" },
  { "id": 1011937, "name": "Курск" },
  { "id": 1011870, "name": "Улан - Удэ" },
  { "id": 1012043, "name": "Ставрополь" },
  { "id": 1011951, "name": "Балашиха" },
  { "id": 1011881, "name": "Магнитогорск" },
  { "id": 1012061, "name": "Тверь" },
  { "id": 1011898, "name": "Иваново" },
  { "id": 1011869, "name": "Брянск" },
  { "id": 1011907, "name": "Сочи" },
  { "id": 1011868, "name": "Белгород" },
  { "id": 1012048, "name": "Нижний Тагил" },
  { "id": 1012073, "name": "Владимир" },
  { "id": 1011859, "name": "Архангельск" },
  { "id": 1011924, "name": "Сургут" },
  { "id": 9040996, "name": "Чита" },
  { "id": 1011928, "name": "Калуга" },
  { "id": 1012038, "name": "Смоленск" },
  { "id": 1012069, "name": "Волжский" },
  { "id": 1011916, "name": "Курган" },
  { "id": 1011990, "name": "Орёл" },
  { "id": 1012074, "name": "Череповец" },
  { "id": 1012075, "name": "Вологда" },
  { "id": 1011950, "name": "Саранск" },
  { "id": 1012037, "name": "Владикавказ" },
  { "id": 1012018, "name": "Якутск" },
  { "id": 1011976, "name": "Мурманск" },
  { "id": 1011963, "name": "Подольск" },
  { "id": 1012057, "name": "Тамбов" },
  { "id": 9040919, "name": "Грозный" },
  { "id": 1011866, "name": "Стерлитамак" },
  { "id": 1011935, "name": "Петрозаводск" },
  { "id": 1011934, "name": "Кострома" },
  { "id": 1011923, "name": "Нижневартовск" },
  { "id": 1011906, "name": "Новороссийск" },
  { "id": 1011949, "name": "Йошкар-Ола" },
  { "id": 9040997, "name": "Комсомольск-на-Амуре" },
  { "id": 1012015, "name": "Таганрог" },
  { "id": 1011931, "name": "Сыктывкар" },
  { "id": 1011956, "name": "Химки" },
  { "id": 1011901, "name": "Нальчик" },
  { "id": 1012014, "name": "Шахты" },
  { "id": 9040952, "name": "Нижнекамск" },
  { "id": 1011895, "name": "Братск" },
  { "id": 1011980, "name": "Дзержинск" },
  { "id": 1011988, "name": "Орск" },
  { "id": 1011894, "name": "Ангарск" },
  { "id": 1011858, "name": "Благовещенск" },
  { "id": 1012034, "name": "Энгельс" },
  { "id": 9040930, "name": "Старый Оскол" },
  { "id": 1011977, "name": "Великий Новгород" },
  { "id": 1011958, "name": "Королёв" },
  { "id": 1012010, "name": "Псков" },
  { "id": 1011854, "name": "Бийск" },
  { "id": 9040982, "name": "Мытищи" },
  { "id": 1011913, "name": "Прокопьевск" },
  { "id": 1012027, "name": "Южно-Сахалинск" },
  { "id": 1012033, "name": "Балаково" },
  { "id": 9040973, "name": "Рыбинск" },
  { "id": 9040927, "name": "Армавир" },
  { "id": 9040939, "name": "Люберцы" },
  { "id": 1011861, "name": "Северодвинск" },
  { "id": 1011899, "name": "Петропавловск-Камчатский" },
  { "id": 1011926, "name": "Абакан" },
  { "id": 1012058, "name": "Норильск" },
  { "id": 1012031, "name": "Сызрань" },
  { "id": 1012016, "name": "Волгодонск" },
  { "id": 1012012, "name": "Новочеркасск" },
  { "id": 1012045, "name": "Каменск - Уральский" },
  { "id": 1011889, "name": "Златоуст" },
  { "id": 1012007, "name": "Уссурийск" },
  { "id": 1011955, "name": "Электросталь" },
  { "id": 1011865, "name": "Салават" },
  { "id": 1012003, "name": "Находка" },
  { "id": 1012053, "name": "Альметьевск" },
  { "id": 1011882, "name": "Миасс" },
  { "id": 1011991, "name": "Березники" },
  { "id": 1011855, "name": "Рубцовск" },
  { "id": 1011878, "name": "Копейск" },
  { "id": 1012042, "name": "Пятигорск" },
  { "id": 9040985, "name": "Красногорск" },
  { "id": 1011852, "name": "Майкоп" },
  { "id": 1011957, "name": "Коломна" },
  { "id": 1011962, "name": "Одинцово" },
  { "id": 1012071, "name": "Ковров" },
  { "id": 9051389, "name": "Хасавюрт" },
  { "id": 9040921, "name": "Кисловодск" },
  { "id": 1011965, "name": "Серпухов" },
  { "id": 9040934, "name": "Новомосковск" },
  { "id": 1011863, "name": "Нефтекамск" },
  { "id": 9051426, "name": "Новочебоксарск" },
  { "id": 1011922, "name": "Нефтеюганск" },
  { "id": 1012049, "name": "Первоуральск" },
  { "id": 9040945, "name": "Щёлково" },
  { "id": 1011902, "name": "Черкесск" },
  { "id": 9040918, "name": "Дербент" },
  { "id": 9051375, "name": "Батайск" },
  { "id": 9040946, "name": "Орехово-Зуево" },
  { "id": 9040926, "name": "Невинномысск" },
  { "id": 9051382, "name": "Домодедово" },
  { "id": 1012066, "name": "Димитровград" },
  { "id": 9051404, "name": "Кызыл" },
  { "id": 9051420, "name": "Назрань" },
  { "id": 9040929, "name": "Камышин" },
  { "id": 1011929, "name": "Обнинск" },
  { "id": 9040958, "name": "Новый Уренгой" },
  { "id": 9051388, "name": "Каспийск" },
  { "id": 1012072, "name": "Муром" },
  { "id": 9040941, "name": "Раменское" },
  { "id": 1011968, "name": "Жуковский" },
  { "id": 1011964, "name": "Пушкино" },
  { "id": 9051428, "name": "Ноябрьск" },
  { "id": 1012041, "name": "Ессентуки" },
  { "id": 9040931, "name": "Елец" },
  { "id": 1011939, "name": "Ачинск" },
  { "id": 9051373, "name": "Артем" },
  { "id": 1011970, "name": "Сергиев Посад" },
  { "id": 1011978, "name": "Арзамас" },
  { "id": 1011927, "name": "Элиста" },
  { "id": 1012028, "name": "Новокуйбышевск" },
  { "id": 1011982, "name": "Бердск" },
  { "id": 1011961, "name": "Ногинск" },
  { "id": 9040983, "name": "Долгопрудный" },
  { "id": 9040956, "name": "Горно-Алтайск" },
  { "id": 1011870, "name": "Улан-Удэ" },
  { "id": 1011948, "name": "Магадан" },
  { "id": 1012085, "name": "Биробиджан" },
  { "id": 9051419, "name": "Нарьян-Мар" },
  { "id": 1011921, "name": "Ханты-Мансийск" },
  { "id": 9067760, "name": "Анадырь" },
  { "id": 1012079, "name": "Салехард" },
  { "id": 21250, "name": "Адыгея" },
  { "id": 20914, "name": "Алтай" },
  { "id": 20918, "name": "Башкортостан" },
  { "id": 20921, "name": "Бурятия" },
  { "id": 20925, "name": "Дагестан" },
  { "id": 21251, "name": "Ингушетия" },
  { "id": 20929, "name": "Кабардино-Балкария" },
  { "id": 21243, "name": "Калмыкия" },
  { "id": 20930, "name": "Карачаево-Черкесия" },
  { "id": 20942, "name": "Карелия" },
  { "id": 20940, "name": "Коми" },
  { "id": 21234, "name": "Марий Эл" },
  { "id": 20948, "name": "Мордовия" },
  { "id": 20963, "name": "Саха (Якутия)" },
  { "id": 21252, "name": "Северная Осетия-Алания" },
  { "id": 20971, "name": "Татарстан" },
  { "id": 21346, "name": "Тыва (Тува)" },
  { "id": 20978, "name": "Удмуртия" },
  { "id": 20938, "name": "Хакасия" },
  { "id": 21347, "name": "Чечня" },
  { "id": 21348, "name": "Чувашия" },
  { "id": 21385, "name": "Алтайский край" },
  { "id": 9047109, "name": "Забайкальский край" },
  { "id": 20928, "name": "Камчатский край" },
  { "id": 20931, "name": "Краснодарский край" },
  { "id": 20944, "name": "Красноярский край" },
  { "id": 20957, "name": "Пермский край" },
  { "id": 20959, "name": "Приморский край" },
  { "id": 20969, "name": "Ставропольский край" },
  { "id": 20935, "name": "Хабаровский край" },
  { "id": 20915, "name": "Амурская область" },
  { "id": 20916, "name": "Архангельская область" },
  { "id": 20917, "name": "Астраханская область" },
  { "id": 20919, "name": "Белгородская область" },
  { "id": 20920, "name": "Брянская область" },
  { "id": 20981, "name": "Владимирская область" },
  { "id": 20980, "name": "Волгоградская область" },
  { "id": 20982, "name": "Вологодская область" },
  { "id": 20983, "name": "Воронежская область" },
  { "id": 20927, "name": "Ивановская область" },
  { "id": 20926, "name": "Иркутская область" },
  { "id": 20933, "name": "Калининградская область" },
  { "id": 20939, "name": "Калужская область" },
  { "id": 20932, "name": "Кемеровская область" },
  { "id": 20937, "name": "Кировская область" },
  { "id": 20941, "name": "Костромская область" },
  { "id": 20934, "name": "Курганская область" },
  { "id": 20943, "name": "Курская область" },
  { "id": 20945, "name": "Ленинградская область" },
  { "id": 20946, "name": "Липецкая область" },
  { "id": 20947, "name": "Магаданская область" },
  { "id": 20949, "name": "Московская область" },
  { "id": 20951, "name": "Мурманская область" },
  { "id": 20953, "name": "Нижегородская область" },
  { "id": 20952, "name": "Новгородская область" },
  { "id": 20954, "name": "Новосибирская область" },
  { "id": 20955, "name": "Омская область" },
  { "id": 20956, "name": "Оренбургская область" },
  { "id": 21256, "name": "Орловская область" },
  { "id": 20958, "name": "Пензенская область" },
  { "id": 20960, "name": "Псковская область" },
  { "id": 20961, "name": "Ростовская область" },
  { "id": 20962, "name": "Рязанская область" },
  { "id": 20965, "name": "Самарская область" },
  { "id": 20966, "name": "Саратовская область" },
  { "id": 20964, "name": "Сахалинская область" },
  { "id": 20970, "name": "Свердловская область" },
  { "id": 20967, "name": "Смоленская область" },
  { "id": 20972, "name": "Тамбовская область" },
  { "id": 20976, "name": "Тверская область" },
  { "id": 20974, "name": "Томская область" },
  { "id": 20975, "name": "Тульская область" },
  { "id": 20977, "name": "Тюменская область" },
  { "id": 20979, "name": "Ульяновская область" },
  { "id": 20922, "name": "Челябинская область" },
  { "id": 20985, "name": "Ярославская область" },
  { "id": 21277, "name": "Еврейская АО" }
]
